winnap/__init__.py
winnap/core.py
winnap-3.1.2.dist-info/METADATA
winnap-3.1.2.dist-info/WHEEL
winnap-3.1.2.dist-info/top_level.txt
winnap-3.1.2.dist-info/RECORD
